pydtfe/__init__.py
pydtfe/pydtfe.py
pydtfe/tests/__init__.py
pydtfe/tests/test_pydtfe.py
pydtfe-2.1.dist-info/METADATA
pydtfe-2.1.dist-info/WHEEL
pydtfe-2.1.dist-info/licenses/LICENSE.txt
pydtfe-2.1.dist-info/RECORD
