Metadata-Version: 2.3
Name: pydtfe
Version: 2.1
Summary: A package that performs the Delaunay Tesselation Field Estimator (DTFE) in 2D and 2D.
Project-URL: Homepage, https://github.com/vicbonj/pydtfe
Author-email: Victor Bonjean <victor.bonjean40@gmail.com>
License-File: LICENSE.txt
Classifier: License :: OSI Approved :: MIT License
Classifier: Operating System :: OS Independent
Classifier: Programming Language :: Python :: 3
Requires-Python: >=3.8
